{
	"displayProperties": {
		"description": "Travel to the Moon and stave off the Hive resurgence alongside your fellow Guardians.",
		"name": "A Mysterious Disturbance",
		"icon": "/img/misc/missing_icon_d2.png",
		"hasIcon": false
	},
	"originalDisplayProperties": {
		"description": "Travel to the Moon and stave off the Hive resurgence alongside your fellow Guardians.",
		"name": "A Mysterious Disturbance",
		"icon": "/img/misc/missing_icon_d2.png",
		"hasIcon": false
	},
	"releaseIcon": "/img/misc/missing_icon_d2.png",
	"releaseTime": 0,
	"activityLevel": 50,
	"completionUnlockHash": 0,
	"activityLightLevel": 760,
	"destinationHash": 290444260,
	"placeHash": 3325508439,
	"activityTypeHash": 1686739444,
	"tier": 1,
	"pgcrImage": "/img/destiny_content/pgcr/story_a_mysterious_disturbance.jpg",
	"rewards": [],
	"modifiers": [],
	"isPlaylist": false,
	"challenges": [],
	"optionalUnlockStrings": [],
	"inheritFromFreeRoam": false,
	"suppressOtherRewards": false,
	"playlistItems": [],
	"matchmaking": {
		"isMatchmade": false,
		"minParty": 1,
		"maxParty": 3,
		"maxPlayers": 3,
		"requiresGuardianOath": false
	},
	"directActivityModeHash": 1686739444,
	"directActivityModeType": 2,
	"loadouts": [],
	"activityModeHashes": [
		1686739444,
		1164760493
	],
	"activityModeTypes": [
		2,
		7
	],
	"isPvP": false,
	"insertionPoints": [
		{
			"phaseHash": 3975719866,
			"unlockHash": 0
		},
		{
			"phaseHash": 3101323696,
			"unlockHash": 0
		}
	],
	"activityLocationMappings": [
		{
			"locationHash": 3377177374,
			"activationSource": "quest",
			"itemHash": 2178015352,
			"activityHash": 2446907856
		}
	],
	"hash": 2446907856,
	"index": 157,
	"redacted": false,
	"blacklisted": false
}