{
    "index": 184, 
    "hash": 1656112293, 
    "blacklisted": false, 
    "avoidDuplicatesOnInitialization": false, 
    "insertAction": {
        "actionSoundHash": 0, 
        "isPositiveAction": false, 
        "actionType": 0, 
        "actionExecuteSeconds": 0
    }, 
    "plugWhitelist": [
        {
            "categoryIdentifier": "tubes", 
            "categoryHash": 1202604782
        }
    ], 
    "currencyScalars": [], 
    "redacted": false, 
    "visibility": 0, 
    "isPreviewEnabled": false, 
    "alwaysRandomizeSockets": false, 
    "overridesUiAppearance": false, 
    "displayProperties": {
        "hasIcon": false, 
        "description": "", 
        "name": ""
    }, 
    "socketCategoryHash": 4241085061, 
    "hideDuplicateReusablePlugs": false
}