{
    "index": 5, 
    "hash": 2584738475, 
    "blacklisted": false, 
    "avoidDuplicatesOnInitialization": false, 
    "insertAction": {
        "actionSoundHash": 0, 
        "isPositiveAction": false, 
        "actionType": 0, 
        "actionExecuteSeconds": 1
    }, 
    "plugWhitelist": [
        {
            "categoryIdentifier": "enhancements.class_titan", 
            "categoryHash": 397607061
        }, 
        {
            "categoryIdentifier": "enhancements.class", 
            "categoryHash": 1955304674
        }, 
        {
            "categoryIdentifier": "enhancements.universal", 
            "categoryHash": 3347429529
        }
    ], 
    "currencyScalars": [], 
    "redacted": false, 
    "visibility": 0, 
    "isPreviewEnabled": false, 
    "alwaysRandomizeSockets": false, 
    "overridesUiAppearance": false, 
    "displayProperties": {
        "hasIcon": false, 
        "description": "", 
        "name": ""
    }, 
    "socketCategoryHash": 590099826, 
    "hideDuplicateReusablePlugs": false
}