{
	"vendorHash": 0,
	"locationReleases": [
		{
			"displayProperties": {
				"description": "",
				"name": "",
				"hasIcon": false
			},
			"spawnPoint": 0,
			"destinationHash": 1199524104,
			"activityHash": 1243390694,
			"activityGraphHash": 109588432,
			"activityGraphNodeHash": 201702215,
			"activityBubbleName": 0,
			"activityPathBundle": 0,
			"activityPathDestination": 0,
			"navPointType": 0,
			"worldPosition": [
				0,
				0,
				0,
				0
			]
		}
	],
	"hash": 884161719,
	"index": 50,
	"redacted": false,
	"blacklisted": false
}