{
	"displayProperties": {
		"description": "In the Crucible, win matches and earn Glory rank \"Fabled.\" Survival and Iron Banner matches grant the most efficient progress. (Iron Banner matches do not grant Glory.)",
		"name": "The Stuff of Myth",
		"icon": "/common/destiny2_content/icons/7cb1b061088e56d62ad003821458b568.png",
		"hasIcon": true
	},
	"scope": 0,
	"objectiveHashes": [
		1400545232,
		1400545233
	],
	"recordValueStyle": 0,
	"titleInfo": {
		"hasTitle": false
	},
	"completionInfo": {
		"partialCompletionObjectiveCountThreshold": 0,
		"ScoreValue": 50,
		"shouldFireToast": true,
		"toastStyle": 1
	},
	"stateInfo": {
		"featuredPriority": 2147483647,
		"completeUnlockHash": 0,
		"claimedUnlockHash": 0
	},
	"requirements": {
		"entitlementUnavailableMessage": ""
	},
	"expirationInfo": {
		"hasExpiration": false,
		"description": ""
	},
	"intervalInfo": {
		"intervalObjectives": [],
		"originalObjectiveArrayInsertionIndex": 0,
		"isIntervalVersionedFromNormalRecord": false
	},
	"rewardItems": [],
	"presentationNodeType": 3,
	"traitIds": [],
	"traitHashes": [],
	"parentNodeHashes": [
		2000731733
	],
	"hash": 1396554507,
	"index": 892,
	"redacted": false,
	"blacklisted": false
}