{
	"displayProperties": {
		"description": "",
		"name": "Finnala's Iron Mark",
		"icon": "/common/destiny2_content/icons/2f12e823749e872990b88d8508e2898a.jpg",
		"hasIcon": true
	},
	"tooltipNotifications": [],
	"backgroundColor": {
		"colorHash": 0,
		"red": 0,
		"green": 0,
		"blue": 0,
		"alpha": 0
	},
	"itemTypeDisplayName": "Titan Mark",
	"uiItemDisplayStyle": "",
	"itemTypeAndTierDisplayName": "Legendary Titan Mark",
	"displaySource": "",
	"inventory": {
		"maxStackSize": 1,
		"bucketTypeHash": 1585787867,
		"recoveryBucketTypeHash": 215593132,
		"tierTypeHash": 4008398120,
		"isInstanceItem": true,
		"nonTransferrableOriginal": false,
		"tierTypeName": "Legendary",
		"tierType": 5,
		"expirationTooltip": "",
		"expiredInActivityMessage": "",
		"expiredInOrbitMessage": "",
		"suppressExpirationWhenObjectivesComplete": true
	},
	"stats": {
		"disablePrimaryStatDisplay": false,
		"stats": {},
		"hasDisplayableStats": false,
		"primaryBaseStatHash": 0
	},
	"equippingBlock": {
		"uniqueLabelHash": 0,
		"equipmentSlotTypeHash": 1585787867,
		"attributes": 0,
		"equippingSoundHash": 0,
		"hornSoundHash": 0,
		"ammoType": 0,
		"displayStrings": []
	},
	"translationBlock": {
		"weaponPatternHash": 0,
		"defaultDyes": [
			{
				"channelHash": 662199250,
				"dyeHash": 2687305800
			},
			{
				"channelHash": 1367384683,
				"dyeHash": 1812589517
			},
			{
				"channelHash": 218592586,
				"dyeHash": 4201619092
			}
		],
		"lockedDyes": [],
		"customDyes": [],
		"arrangements": [
			{
				"classHash": 0,
				"artArrangementHash": 1348124581
			}
		],
		"hasGeometry": true
	},
	"quality": {
		"itemLevels": [],
		"qualityLevel": 0,
		"infusionCategoryName": "0",
		"infusionCategoryHash": 0,
		"infusionCategoryHashes": [],
		"progressionLevelRequirementHash": 0,
		"currentVersion": 0,
		"versions": [
			{
				"powerCapHash": 1862490583
			}
		],
		"displayVersionWatermarkIcons": [
			""
		]
	},
	"acquireRewardSiteHash": 0,
	"acquireUnlockHash": 0,
	"investmentStats": [],
	"perks": [],
	"summaryItemHash": 3407672161,
	"allowActions": true,
	"doesPostmasterPullHaveSideEffects": false,
	"nonTransferrable": false,
	"itemCategoryHashes": [
		49,
		20,
		3109687656
	],
	"specialItemType": 0,
	"itemType": 20,
	"itemSubType": 30,
	"classType": 3,
	"breakerType": 0,
	"equippable": true,
	"defaultDamageType": 0,
	"isWrapper": false,
	"traitIds": [
		"armor_type.class",
		"item_type.armor"
	],
	"hash": 2472429927,
	"index": 4074,
	"redacted": false,
	"blacklisted": false
}