{
	"displayProperties": {
		"description": "Random Perks: This item cannot be reacquired from Collections.",
		"name": "Dreambane Hood",
		"icon": "/common/destiny2_content/icons/2a729cf899e03f8bcb6299d6f9cdd195.jpg",
		"hasIcon": true
	},
	"tooltipNotifications": [],
	"backgroundColor": {
		"colorHash": 0,
		"red": 0,
		"green": 0,
		"blue": 0,
		"alpha": 0
	},
	"itemTypeDisplayName": "Helmet",
	"uiItemDisplayStyle": "",
	"itemTypeAndTierDisplayName": "Legendary Helmet",
	"displaySource": "\"And lastly, a shroud of dreams, so that you might see these nightmares with open eyes.\" —Eris Morn",
	"action": {
		"verbName": "Dismantle",
		"verbDescription": "",
		"isPositive": false,
		"requiredCooldownSeconds": 0,
		"requiredItems": [],
		"progressionRewards": [],
		"actionTypeLabel": "shard",
		"rewardSheetHash": 0,
		"rewardItemHash": 0,
		"rewardSiteHash": 0,
		"requiredCooldownHash": 0,
		"deleteOnAction": true,
		"consumeEntireStack": false,
		"useOnAcquire": true
	},
	"inventory": {
		"maxStackSize": 1,
		"bucketTypeHash": 3448274439,
		"recoveryBucketTypeHash": 0,
		"tierTypeHash": 4008398120,
		"isInstanceItem": true,
		"nonTransferrableOriginal": false,
		"tierTypeName": "Legendary",
		"tierType": 5,
		"expirationTooltip": "",
		"expiredInActivityMessage": "",
		"expiredInOrbitMessage": "",
		"suppressExpirationWhenObjectivesComplete": true
	},
	"stats": {
		"disablePrimaryStatDisplay": false,
		"statGroupHash": 1116828683,
		"stats": {
			"1885944937": {
				"statHash": 1885944937,
				"value": 0,
				"minimum": 0,
				"maximum": 0,
				"displayMaximum": 42
			},
			"1935470627": {
				"statHash": 1935470627,
				"value": 0,
				"minimum": 0,
				"maximum": 0,
				"displayMaximum": 42
			},
			"3897883278": {
				"statHash": 3897883278,
				"value": 0,
				"minimum": 0,
				"maximum": 0,
				"displayMaximum": 42
			}
		},
		"hasDisplayableStats": false,
		"primaryBaseStatHash": 3897883278
	},
	"equippingBlock": {
		"uniqueLabelHash": 0,
		"equipmentSlotTypeHash": 3448274439,
		"attributes": 0,
		"equippingSoundHash": 0,
		"hornSoundHash": 0,
		"ammoType": 0,
		"displayStrings": [
			""
		]
	},
	"translationBlock": {
		"weaponPatternHash": 0,
		"defaultDyes": [
			{
				"channelHash": 662199250,
				"dyeHash": 481449539
			},
			{
				"channelHash": 1367384683,
				"dyeHash": 1577528110
			},
			{
				"channelHash": 218592586,
				"dyeHash": 3768002581
			}
		],
		"lockedDyes": [],
		"customDyes": [],
		"arrangements": [
			{
				"classHash": 0,
				"artArrangementHash": 1528483180
			}
		],
		"hasGeometry": true
	},
	"preview": {
		"screenStyle": "screen_style_sockets",
		"previewVendorHash": 0,
		"previewActionString": ""
	},
	"quality": {
		"itemLevels": [],
		"qualityLevel": 0,
		"infusionCategoryName": "1046741990",
		"infusionCategoryHash": 1046741990,
		"infusionCategoryHashes": [
			1046741990
		],
		"progressionLevelRequirementHash": 3768955166,
		"currentVersion": 0,
		"versions": [
			{
				"powerCapHash": 1862490584
			}
		],
		"displayVersionWatermarkIcons": [
			""
		]
	},
	"acquireRewardSiteHash": 0,
	"acquireUnlockHash": 0,
	"sockets": {
		"detail": "Details",
		"socketEntries": [
			{
				"socketTypeHash": 1718047805,
				"singleInitialItemHash": 481675395,
				"reusablePlugItems": [],
				"preventInitializationOnVendorPurchase": false,
				"preventInitializationWhenVersioning": false,
				"hidePerksInItemTooltip": false,
				"plugSources": 13,
				"reusablePlugSetHash": 3559124992,
				"overridesUiAppearance": false,
				"defaultVisible": true
			},
			{
				"socketTypeHash": 968742181,
				"singleInitialItemHash": 807186981,
				"reusablePlugItems": [],
				"preventInitializationOnVendorPurchase": false,
				"preventInitializationWhenVersioning": false,
				"hidePerksInItemTooltip": false,
				"plugSources": 13,
				"reusablePlugSetHash": 2844132982,
				"overridesUiAppearance": false,
				"defaultVisible": true
			},
			{
				"socketTypeHash": 968742181,
				"singleInitialItemHash": 807186981,
				"reusablePlugItems": [],
				"preventInitializationOnVendorPurchase": false,
				"preventInitializationWhenVersioning": false,
				"hidePerksInItemTooltip": false,
				"plugSources": 13,
				"reusablePlugSetHash": 2844132982,
				"overridesUiAppearance": false,
				"defaultVisible": true
			},
			{
				"socketTypeHash": 4127539203,
				"singleInitialItemHash": 2620967748,
				"reusablePlugItems": [],
				"preventInitializationOnVendorPurchase": false,
				"preventInitializationWhenVersioning": false,
				"hidePerksInItemTooltip": false,
				"plugSources": 5,
				"reusablePlugSetHash": 764967870,
				"overridesUiAppearance": false,
				"defaultVisible": true
			},
			{
				"socketTypeHash": 2321980680,
				"singleInitialItemHash": 4248210736,
				"reusablePlugItems": [],
				"preventInitializationOnVendorPurchase": false,
				"preventInitializationWhenVersioning": false,
				"hidePerksInItemTooltip": false,
				"plugSources": 7,
				"reusablePlugSetHash": 4,
				"overridesUiAppearance": false,
				"defaultVisible": true
			},
			{
				"socketTypeHash": 0,
				"singleInitialItemHash": 0,
				"reusablePlugItems": [],
				"preventInitializationOnVendorPurchase": false,
				"preventInitializationWhenVersioning": false,
				"hidePerksInItemTooltip": false,
				"plugSources": 1,
				"overridesUiAppearance": false,
				"defaultVisible": false
			},
			{
				"socketTypeHash": 1489351422,
				"singleInitialItemHash": 3135249387,
				"reusablePlugItems": [],
				"preventInitializationOnVendorPurchase": true,
				"preventInitializationWhenVersioning": false,
				"hidePerksInItemTooltip": false,
				"plugSources": 1,
				"overridesUiAppearance": false,
				"defaultVisible": false
			},
			{
				"socketTypeHash": 1489351422,
				"singleInitialItemHash": 3816367703,
				"reusablePlugItems": [],
				"preventInitializationOnVendorPurchase": true,
				"preventInitializationWhenVersioning": false,
				"hidePerksInItemTooltip": false,
				"plugSources": 1,
				"overridesUiAppearance": false,
				"defaultVisible": false
			},
			{
				"socketTypeHash": 1489351422,
				"singleInitialItemHash": 757147114,
				"reusablePlugItems": [],
				"preventInitializationOnVendorPurchase": true,
				"preventInitializationWhenVersioning": false,
				"hidePerksInItemTooltip": false,
				"plugSources": 1,
				"overridesUiAppearance": false,
				"defaultVisible": false
			},
			{
				"socketTypeHash": 1489351422,
				"singleInitialItemHash": 4085212425,
				"reusablePlugItems": [],
				"preventInitializationOnVendorPurchase": true,
				"preventInitializationWhenVersioning": false,
				"hidePerksInItemTooltip": false,
				"plugSources": 1,
				"overridesUiAppearance": false,
				"defaultVisible": false
			},
			{
				"socketTypeHash": 2485466462,
				"singleInitialItemHash": 702981643,
				"reusablePlugItems": [
					{
						"plugItemHash": 2520561932
					},
					{
						"plugItemHash": 4075989867
					},
					{
						"plugItemHash": 3388638931
					},
					{
						"plugItemHash": 3905287389
					},
					{
						"plugItemHash": 2516513295
					},
					{
						"plugItemHash": 3999699118
					},
					{
						"plugItemHash": 1518774295
					},
					{
						"plugItemHash": 1518774294
					},
					{
						"plugItemHash": 1397648181
					},
					{
						"plugItemHash": 3909176373
					},
					{
						"plugItemHash": 1575996367
					},
					{
						"plugItemHash": 3170681623
					},
					{
						"plugItemHash": 3590187517
					},
					{
						"plugItemHash": 2412534419
					},
					{
						"plugItemHash": 1681122628
					},
					{
						"plugItemHash": 84296096
					},
					{
						"plugItemHash": 948716319
					},
					{
						"plugItemHash": 2338851618
					}
				],
				"preventInitializationOnVendorPurchase": false,
				"preventInitializationWhenVersioning": false,
				"hidePerksInItemTooltip": false,
				"plugSources": 7,
				"reusablePlugSetHash": 709078552,
				"overridesUiAppearance": false,
				"defaultVisible": true
			}
		],
		"intrinsicSockets": [
			{
				"plugItemHash": 3690882495,
				"socketTypeHash": 1049510759,
				"defaultVisible": true
			}
		],
		"socketCategories": [
			{
				"socketCategoryHash": 590099826,
				"socketIndexes": [
					0,
					1,
					2,
					3
				]
			},
			{
				"socketCategoryHash": 1926152773,
				"socketIndexes": [
					4,
					10
				]
			},
			{
				"socketCategoryHash": 3154740035,
				"socketIndexes": [
					6,
					7,
					8,
					9
				]
			}
		]
	},
	"talentGrid": {
		"talentGridHash": 521135891,
		"itemDetailString": "Details",
		"hudDamageType": 1
	},
	"investmentStats": [
		{
			"statTypeHash": 3897883278,
			"value": 0,
			"isConditionallyActive": false
		},
		{
			"statTypeHash": 1935470627,
			"value": 0,
			"isConditionallyActive": false
		},
		{
			"statTypeHash": 1885944937,
			"value": 0,
			"isConditionallyActive": false
		}
	],
	"perks": [],
	"summaryItemHash": 3407672161,
	"allowActions": true,
	"doesPostmasterPullHaveSideEffects": true,
	"nonTransferrable": false,
	"itemCategoryHashes": [
		21,
		45,
		20,
		3109687656
	],
	"specialItemType": 0,
	"itemType": 20,
	"itemSubType": 26,
	"classType": 2,
	"breakerType": 0,
	"equippable": true,
	"defaultDamageType": 0,
	"isWrapper": false,
	"traitIds": [
		"armor_type.head",
		"item_type.armor"
	],
	"hash": 4166880830,
	"index": 10520,
	"redacted": false,
	"blacklisted": false
}