{
	"displayProperties": {
		"description": "Unlocks the ability to focus Umbral Engrams, allowing a Guardian to choose the primary stat of the armor contained within.",
		"name": "Improved Armor Focusing",
		"icon": "/common/destiny2_content/icons/ed5bcc89be6e7abd09a24c464ed4b46d.jpg",
		"iconSequences": [
			{
				"frames": [
					"/common/destiny2_content/icons/ed5bcc89be6e7abd09a24c464ed4b46d.jpg"
				]
			},
			{
				"frames": [
					"/common/destiny2_content/icons/79c90d6db6210032f771525a5710e374.png"
				]
			}
		],
		"hasIcon": true
	},
	"tooltipNotifications": [
		{
			"displayString": "Expires at the end of Season of Arrivals",
			"displayStyle": ""
		}
	],
	"backgroundColor": {
		"colorHash": 0,
		"red": 0,
		"green": 0,
		"blue": 0,
		"alpha": 0
	},
	"itemTypeDisplayName": "Season of Arrivals Perk",
	"uiItemDisplayStyle": "",
	"itemTypeAndTierDisplayName": "Common Season of Arrivals Perk",
	"displaySource": "",
	"tooltipStyle": "vendor_action",
	"action": {
		"verbName": "Discard",
		"verbDescription": "",
		"isPositive": false,
		"requiredCooldownSeconds": 0,
		"requiredItems": [],
		"progressionRewards": [],
		"actionTypeLabel": "shard",
		"rewardSheetHash": 0,
		"rewardItemHash": 0,
		"rewardSiteHash": 0,
		"requiredCooldownHash": 0,
		"deleteOnAction": true,
		"consumeEntireStack": true,
		"useOnAcquire": false
	},
	"inventory": {
		"maxStackSize": 1,
		"bucketTypeHash": 2422292810,
		"recoveryBucketTypeHash": 0,
		"tierTypeHash": 3340296461,
		"isInstanceItem": false,
		"nonTransferrableOriginal": false,
		"tierTypeName": "Common",
		"tierType": 2,
		"expirationTooltip": "",
		"expiredInActivityMessage": "",
		"expiredInOrbitMessage": "",
		"suppressExpirationWhenObjectivesComplete": true
	},
	"acquireRewardSiteHash": 0,
	"acquireUnlockHash": 0,
	"investmentStats": [],
	"perks": [],
	"allowActions": true,
	"doesPostmasterPullHaveSideEffects": false,
	"nonTransferrable": true,
	"itemCategoryHashes": [
		3109687656
	],
	"specialItemType": 0,
	"itemType": 20,
	"itemSubType": 0,
	"classType": 3,
	"breakerType": 0,
	"equippable": false,
	"defaultDamageType": 0,
	"isWrapper": false,
	"traitIds": [
		"item_type.boost"
	],
	"hash": 889395851,
	"index": 12532,
	"redacted": false,
	"blacklisted": false
}