{
    "index": 761, 
    "hash": 204, 
    "blacklisted": false, 
    "redacted": false, 
    "reusablePlugItems": [
        {
            "alternateWeight": 0.0, 
            "weight": 0.0, 
            "plugItemHash": 702981643
        }, 
        {
            "alternateWeight": 0.0, 
            "weight": 0.0, 
            "plugItemHash": 3377623014
        }, 
        {
            "alternateWeight": 0.0, 
            "weight": 0.0, 
            "plugItemHash": 3167890668
        }
    ], 
    "isFakePlugSet": true
}