{
    "index": 65, 
    "hash": 2161711907, 
    "blacklisted": false, 
    "redacted": false, 
    "reusablePlugItems": [
        {
            "alternateWeight": 0.0, 
            "weight": 0.0, 
            "plugItemHash": 1316177012
        }, 
        {
            "alternateWeight": 0.0, 
            "weight": 0.0, 
            "plugItemHash": 2760701299
        }, 
        {
            "alternateWeight": 0.0, 
            "weight": 0.0, 
            "plugItemHash": 673846245
        }, 
        {
            "alternateWeight": 0.0, 
            "weight": 0.0, 
            "plugItemHash": 3416944458
        }, 
        {
            "alternateWeight": 0.0, 
            "weight": 0.0, 
            "plugItemHash": 310410239
        }, 
        {
            "alternateWeight": 0.0, 
            "weight": 0.0, 
            "plugItemHash": 3317098328
        }
    ], 
    "isFakePlugSet": false, 
    "displayProperties": {
        "hasIcon": false, 
        "description": "", 
        "name": ""
    }
}