{
    "index": 259, 
    "hash": 2539715782, 
    "blacklisted": false, 
    "redacted": false, 
    "reusablePlugItems": [
        {
            "alternateWeight": 0.0, 
            "weight": 0.0, 
            "plugItemHash": 3425386926
        }, 
        {
            "alternateWeight": 0.0, 
            "weight": 0.0, 
            "plugItemHash": 706527188
        }, 
        {
            "alternateWeight": 0.0, 
            "weight": 0.0, 
            "plugItemHash": 588594999
        }, 
        {
            "alternateWeight": 0.0, 
            "weight": 0.0, 
            "plugItemHash": 3300816228
        }
    ], 
    "isFakePlugSet": false, 
    "displayProperties": {
        "hasIcon": false, 
        "description": "", 
        "name": ""
    }
}