{
    "index": 145, 
    "redacted": false, 
    "materials": [
        {
            "count": 500, 
            "deleteOnAction": true, 
            "itemHash": 3159615086, 
            "omitFromRequirements": true
        }, 
        {
            "count": 5, 
            "deleteOnAction": true, 
            "itemHash": 1022552290, 
            "omitFromRequirements": true
        }, 
        {
            "count": 5, 
            "deleteOnAction": true, 
            "itemHash": 685157383, 
            "omitFromRequirements": true
        }, 
        {
            "count": 7, 
            "deleteOnAction": true, 
            "itemHash": 3853748946, 
            "omitFromRequirements": true
        }
    ], 
    "hash": 1096424763, 
    "blacklisted": false
}