{
	"displayProperties": {
		"description": "Say again? You ask, are we alone here? You mean to ask if we are the only good that lives in the light of our sun, do you not? You mean to ask, do we have allies? Do we have distant allies, ignoring our plight, either too weak to fight or too afraid to show their faces? \n\nI, too, have been cursed by these questions. \n\nWhat if I told you that eons beyond the void lie worlds that do yearn to aid in our struggle? What if I told you there is a way to grant them passage into your mind, to let them guide your eye against our one true enemy? That they have told me that the dusk of the pyramid draws nigh? Would you believe me? \n\nFool!",
		"name": "Eye of Another World",
		"hasIcon": false
	},
	"subtitle": "When the universe conspires, its enemies cannot hide.",
	"hash": 2523259392,
	"index": 87,
	"redacted": false,
	"blacklisted": false
}