{
    "sourceHash": 2653618435, 
    "sourceString": "Source: Leviathan raid.", 
    "blacklisted": false, 
    "acquisitionInfo": {
        "runOnlyAcquisitionRewardSite": false, 
        "acquireMaterialRequirementHash": 983547049
    }, 
    "index": 4702, 
    "presentationNodeType": 2, 
    "traitHashes": [], 
    "redacted": false, 
    "stateInfo": {
        "requirements": {
            "entitlementUnavailableMessage": ""
        }
    }, 
    "parentNodeHashes": [
        1604869479
    ], 
    "traitIds": [], 
    "displayProperties": {
        "icon": "/common/destiny2_content/icons/8ba6a44f16129231360d2910e60a0268.jpg", 
        "hasIcon": true, 
        "description": "At the edge of the universe, I stared into the infinite deep. It stared back, and was pleased. I would become the herald of its victory, and bear witness for all creation.", 
        "name": "It Stared Back"
    }, 
    "scope": 0, 
    "itemHash": 1018072983, 
    "hash": 1088431377
}