{
	"displayProperties": {
		"description": "\"All we have left now is our faith.\"",
		"name": "Traveler's Chosen",
		"icon": "/common/destiny2_content/icons/82e9861f705e856ff4e339cd19447d4f.jpg",
		"hasIcon": true
	},
	"scope": 0,
	"sourceString": "Source: An Exotic quest or challenge.",
	"sourceHash": 1957611613,
	"itemHash": 1853180924,
	"acquisitionInfo": {
		"acquireMaterialRequirementHash": 1920773870,
		"runOnlyAcquisitionRewardSite": false
	},
	"stateInfo": {
		"requirements": {
			"entitlementUnavailableMessage": ""
		}
	},
	"presentationNodeType": 2,
	"traitIds": [],
	"traitHashes": [],
	"parentNodeHashes": [
		1996848060,
		582419680,
		1840210717,
		2969886327
	],
	"hash": 1370087379,
	"index": 2202,
	"redacted": false,
	"blacklisted": false
}