{
    "sourceHash": 1216155659, 
    "sourceString": "Source: Complete the \"Season 8: First Watch\" quest.", 
    "blacklisted": false, 
    "acquisitionInfo": {
        "runOnlyAcquisitionRewardSite": false, 
        "acquireMaterialRequirementHash": 1921496923
    }, 
    "index": 3469, 
    "presentationNodeType": 1, 
    "traitHashes": [], 
    "redacted": false, 
    "stateInfo": {
        "requirements": {
            "entitlementUnavailableMessage": ""
        }
    }, 
    "parentNodeHashes": [
        4107433557, 
        805054563, 
        3083337344, 
        2063190939
    ], 
    "traitIds": [], 
    "displayProperties": {
        "icon": "/common/destiny2_content/icons/54b0d83312ccd176e7390a3287bff5d5.jpg", 
        "hasIcon": true, 
        "description": "Equip this shader to change the color of your gear.", 
        "name": "Vanguard Angelos"
    }, 
    "scope": 0, 
    "itemHash": 2058800853, 
    "hash": 1453685850
}