{
	"displayProperties": {
		"description": "The plains outside the City are marred by the bones of downed ships, both Guardian and Cabal.",
		"name": "Holdfast Boots",
		"icon": "/common/destiny2_content/icons/f4cc51d61caa5e0bd4e04fe716f44674.jpg",
		"hasIcon": true
	},
	"scope": 1,
	"sourceString": "Source: Season Pass Reward",
	"sourceHash": 1593696611,
	"itemHash": 674876967,
	"acquisitionInfo": {
		"runOnlyAcquisitionRewardSite": false
	},
	"stateInfo": {
		"requirements": {
			"entitlementUnavailableMessage": ""
		}
	},
	"presentationNodeType": 2,
	"traitIds": [],
	"traitHashes": [],
	"parentNodeHashes": [
		548595816,
		1840210717
	],
	"hash": 1461111453,
	"index": 1729,
	"redacted": false,
	"blacklisted": false
}