{
	"displayProperties": {
		"description": "Please be advised, you must file form 7C and 9D upon each use.",
		"name": "Bureaucratic Walk",
		"icon": "/common/destiny2_content/icons/b709643098018b2714e6442f7bc36eba.jpg",
		"hasIcon": true
	},
	"scope": 0,
	"sourceString": "Source: Bright Engrams.",
	"sourceHash": 4036739795,
	"itemHash": 930064526,
	"acquisitionInfo": {
		"runOnlyAcquisitionRewardSite": false
	},
	"stateInfo": {
		"requirements": {
			"entitlementUnavailableMessage": ""
		}
	},
	"presentationNodeType": 1,
	"traitIds": [],
	"traitHashes": [],
	"parentNodeHashes": [
		304361726
	],
	"hash": 1700163281,
	"index": 3532,
	"redacted": false,
	"blacklisted": false
}