{
    "sourceHash": 3389857033, 
    "sourceString": "", 
    "blacklisted": false, 
    "acquisitionInfo": {
        "runOnlyAcquisitionRewardSite": false
    }, 
    "index": 1727, 
    "presentationNodeType": 2, 
    "traitHashes": [], 
    "redacted": false, 
    "stateInfo": {
        "requirements": {
            "entitlementUnavailableMessage": ""
        }
    }, 
    "parentNodeHashes": [
        2389993859
    ], 
    "traitIds": [], 
    "displayProperties": {
        "icon": "/common/destiny2_content/icons/14c00b72ba87b4ea614ae3109e3f00b7.jpg", 
        "hasIcon": true, 
        "description": "Complete weekly strike milestones during Season 2 to earn this ornament. It is unlocked to the Took Offense, Shelter in Place, and Xenos Vale IV chest armor.", 
        "name": "Xenos Shore Ornament"
    }, 
    "scope": 0, 
    "itemHash": 2033661183, 
    "hash": 1895678786
}