{
	"displayProperties": {
		"description": "\"Long live the Queen.\" —Petra Venj",
		"name": "Vestian Dynasty",
		"icon": "/common/destiny2_content/icons/c5192c8f06b487dd53ee6907284837e1.jpg",
		"hasIcon": true
	},
	"scope": 0,
	"sourceString": "Source: Earned over the course of the Forsaken campaign.",
	"sourceHash": 3532642391,
	"itemHash": 3334276332,
	"acquisitionInfo": {
		"acquireMaterialRequirementHash": 983547049,
		"runOnlyAcquisitionRewardSite": false
	},
	"stateInfo": {
		"requirements": {
			"entitlementUnavailableMessage": ""
		}
	},
	"presentationNodeType": 2,
	"traitIds": [],
	"traitHashes": [],
	"parentNodeHashes": [
		3779085124
	],
	"hash": 2219212005,
	"index": 4918,
	"redacted": false,
	"blacklisted": false
}