{
	"displayProperties": {
		"description": "",
		"name": "Saladin's Pride",
		"icon": "/common/destiny2_content/icons/606ed4223d6eb9c12376602dacf0c014.jpg",
		"hasIcon": true
	},
	"scope": 0,
	"sourceString": "Reached level 5 in the Ages of Triumph record book.",
	"sourceHash": 1462687159,
	"itemHash": 4077939642,
	"acquisitionInfo": {
		"runOnlyAcquisitionRewardSite": false
	},
	"stateInfo": {
		"requirements": {
			"entitlementUnavailableMessage": ""
		}
	},
	"presentationNodeType": 1,
	"traitIds": [],
	"traitHashes": [],
	"parentNodeHashes": [
		1166184619
	],
	"hash": 2259574267,
	"index": 3084,
	"redacted": false,
	"blacklisted": false
}