{
	"displayProperties": {
		"description": "Joy is up to you. Take it and fly.",
		"name": "Joyfire",
		"icon": "/common/destiny2_content/icons/b118e6a3959e8ab49710a0d1c96b9b9b.jpg",
		"hasIcon": true
	},
	"scope": 0,
	"sourceString": "Source: Bright Engrams.",
	"sourceHash": 4036739795,
	"itemHash": 3140833554,
	"acquisitionInfo": {
		"acquireMaterialRequirementHash": 2082271808,
		"runOnlyAcquisitionRewardSite": false
	},
	"stateInfo": {
		"requirements": {
			"entitlementUnavailableMessage": ""
		}
	},
	"presentationNodeType": 1,
	"traitIds": [],
	"traitHashes": [],
	"parentNodeHashes": [
		2293479498
	],
	"hash": 2448009823,
	"index": 4062,
	"redacted": false,
	"blacklisted": false
}