{
	"displayProperties": {
		"description": "I wish to be strategic.",
		"name": "Helm of the Great Hunt",
		"icon": "/common/destiny2_content/icons/c9ff2846a1474f315305e4f9bc413b2e.jpg",
		"hasIcon": true
	},
	"scope": 1,
	"sourceString": "Source: Last Wish raid.",
	"sourceHash": 2455011338,
	"itemHash": 2274520361,
	"acquisitionInfo": {
		"runOnlyAcquisitionRewardSite": false
	},
	"stateInfo": {
		"requirements": {
			"entitlementUnavailableMessage": ""
		}
	},
	"presentationNodeType": 2,
	"traitIds": [],
	"traitHashes": [],
	"parentNodeHashes": [
		1847361717,
		558738844
	],
	"hash": 28595,
	"index": 877,
	"redacted": false,
	"blacklisted": false
}