{
    "sourceHash": 3334812276, 
    "sourceString": "Source: Open Legendary engrams and earn faction rank-up packages.", 
    "blacklisted": false, 
    "acquisitionInfo": {
        "runOnlyAcquisitionRewardSite": false, 
        "acquireMaterialRequirementHash": 983547049
    }, 
    "index": 1188, 
    "presentationNodeType": 2, 
    "traitHashes": [], 
    "redacted": false, 
    "stateInfo": {
        "requirements": {
            "entitlementUnavailableMessage": ""
        }
    }, 
    "parentNodeHashes": [
        2666464326
    ], 
    "traitIds": [], 
    "displayProperties": {
        "icon": "/common/destiny2_content/icons/0726b93f7ffb1936ea41739d0a71bc0f.jpg", 
        "hasIcon": true, 
        "description": "\"Use your surroundings, they said. Don't think they meant 'build armor out of a crashed space base,' but here we are.\"", 
        "name": "Terra Concord Fists"
    }, 
    "scope": 1, 
    "itemHash": 3999262583, 
    "hash": 2969017293
}