{
    "sourceHash": 3389857033, 
    "sourceString": "", 
    "blacklisted": false, 
    "acquisitionInfo": {
        "runOnlyAcquisitionRewardSite": false
    }, 
    "index": 922, 
    "presentationNodeType": 2, 
    "traitHashes": [], 
    "redacted": false, 
    "stateInfo": {
        "requirements": {
            "entitlementUnavailableMessage": ""
        }
    }, 
    "parentNodeHashes": [
        4124408557
    ], 
    "traitIds": [], 
    "displayProperties": {
        "icon": "/common/destiny2_content/icons/00824cb3a00a4499f30ff058de099233.jpg", 
        "hasIcon": true, 
        "description": "Claim Dead Orbit reward engrams in Season 2 to earn this ornament. It is unlocked to the Stella Incognita Cloak, Mark, and Bond.", 
        "name": "Extinction Orbit Ornament"
    }, 
    "scope": 0, 
    "itemHash": 1936477944, 
    "hash": 3072800063
}