{
    "sourceHash": 1675483099, 
    "sourceString": "Source: Leviathan, Spire of Stars raid lair.", 
    "blacklisted": false, 
    "acquisitionInfo": {
        "runOnlyAcquisitionRewardSite": false
    }, 
    "index": 2948, 
    "presentationNodeType": 1, 
    "traitHashes": [], 
    "redacted": false, 
    "stateInfo": {
        "requirements": {
            "entitlementUnavailableMessage": ""
        }
    }, 
    "parentNodeHashes": [
        329982304
    ], 
    "traitIds": [], 
    "displayProperties": {
        "icon": "/common/destiny2_content/icons/70422198861e09744fbc020bf1925be5.jpg", 
        "hasIcon": true, 
        "description": "", 
        "name": "Spire Star"
    }, 
    "scope": 0, 
    "itemHash": 1057119308, 
    "hash": 3125541831
}