{
    "sourceHash": 3389857033, 
    "sourceString": "", 
    "blacklisted": false, 
    "acquisitionInfo": {
        "runOnlyAcquisitionRewardSite": false
    }, 
    "index": 1481, 
    "presentationNodeType": 2, 
    "traitHashes": [], 
    "redacted": false, 
    "stateInfo": {
        "requirements": {
            "entitlementUnavailableMessage": ""
        }
    }, 
    "parentNodeHashes": [
        2009783228
    ], 
    "traitIds": [], 
    "displayProperties": {
        "icon": "/common/destiny2_content/icons/8b1bc6bcf6ddce96174b177a35e0f9df.jpg", 
        "hasIcon": true, 
        "description": "Complete \"Spire of Stars\" on Prestige difficulty in Season 3 to unlock and equip this ornament.", 
        "name": "Praetorian Ornament"
    }, 
    "scope": 0, 
    "itemHash": 430065393, 
    "hash": 3171962093
}