{
	"displayProperties": {
		"description": "Claim Vanguard Tactician reward engrams during Season 2 to earn this ornament. It's unlocked for all Crucible armor sets.",
		"name": "Soaring Sword Ornament",
		"icon": "/common/destiny2_content/icons/a8060f57b3d245091e585a2e46dda5e7.jpg",
		"hasIcon": true
	},
	"scope": 0,
	"sourceString": "",
	"sourceHash": 3389857033,
	"itemHash": 1181382726,
	"acquisitionInfo": {
		"runOnlyAcquisitionRewardSite": false
	},
	"stateInfo": {
		"requirements": {
			"entitlementUnavailableMessage": ""
		}
	},
	"presentationNodeType": 2,
	"traitIds": [],
	"traitHashes": [],
	"parentNodeHashes": [
		1633867911
	],
	"hash": 3178834489,
	"index": 9,
	"redacted": false,
	"blacklisted": false
}