{
    "sourceHash": 1373723300, 
    "sourceString": "Source: Complete activities and earn rank-up packages in the EDZ.", 
    "blacklisted": false, 
    "acquisitionInfo": {
        "runOnlyAcquisitionRewardSite": false, 
        "acquireMaterialRequirementHash": 983547049
    }, 
    "index": 1099, 
    "presentationNodeType": 2, 
    "traitHashes": [], 
    "redacted": false, 
    "stateInfo": {
        "requirements": {
            "entitlementUnavailableMessage": ""
        }
    }, 
    "parentNodeHashes": [
        3952745166, 
        1893032045
    ], 
    "traitIds": [], 
    "displayProperties": {
        "icon": "/common/destiny2_content/icons/1895a80a842785bee949c7403544a065.jpg", 
        "hasIcon": true, 
        "description": "\"I love the City. But I don't want to go back. I want to bring the City to the EDZ.\" —Devrim Kay", 
        "name": "Wildwood Helm"
    }, 
    "scope": 1, 
    "itemHash": 3080875433, 
    "hash": 3349346106
}