{
    "sourceHash": 3532642391, 
    "sourceString": "Source: Earned over the course of the Forsaken campaign.", 
    "blacklisted": false, 
    "acquisitionInfo": {
        "runOnlyAcquisitionRewardSite": false
    }, 
    "index": 1827, 
    "presentationNodeType": 2, 
    "traitHashes": [], 
    "redacted": false, 
    "stateInfo": {
        "requirements": {
            "entitlementUnavailableMessage": ""
        }
    }, 
    "parentNodeHashes": [
        2983784775
    ], 
    "traitIds": [], 
    "displayProperties": {
        "icon": "/common/destiny2_content/icons/64889af0bf2a54393020586e70696003.jpg", 
        "hasIcon": true, 
        "description": "\"Hey… take me with you.\" —Cayde-6", 
        "name": "Memory of Cayde"
    }, 
    "scope": 1, 
    "itemHash": 1014677029, 
    "hash": 524374393
}