{
	"displayProperties": {
		"description": "To warm our bodies in the chill of the night.",
		"name": "Iron Remembrance Plate",
		"icon": "/common/destiny2_content/icons/8a5d136540b0dbfcd37b6667e2fa47ed.jpg",
		"hasIcon": true
	},
	"scope": 1,
	"sourceString": "Source: Complete Iron Banner matches and earn rank-up packages from Lord Saladin.",
	"sourceHash": 3072862693,
	"itemHash": 741704251,
	"acquisitionInfo": {
		"runOnlyAcquisitionRewardSite": false
	},
	"stateInfo": {
		"requirements": {
			"entitlementUnavailableMessage": ""
		}
	},
	"presentationNodeType": 2,
	"traitIds": [],
	"traitHashes": [],
	"parentNodeHashes": [
		3029715667
	],
	"hash": 614324690,
	"index": 734,
	"redacted": false,
	"blacklisted": false
}