{
	"displayProperties": {
		"description": "Complete a Nightmare Hunt on Master difficulty.",
		"name": "Weekly Pinnacle Challenge",
		"hasIcon": false
	},
	"unlockValueHash": 0,
	"completionValue": 1,
	"scope": 4,
	"locationHash": 0,
	"allowNegativeValue": false,
	"allowValueChangeWhenCompleted": false,
	"isCountingDownward": false,
	"valueStyle": 0,
	"progressDescription": "Nightmare Hunts completed",
	"perks": {
		"perkHash": 0,
		"style": 0
	},
	"stats": {
		"style": 0
	},
	"minimumVisibilityThreshold": -2147483648,
	"allowOvercompletion": false,
	"showValueOnComplete": false,
	"isDisplayOnlyObjective": false,
	"completedValueStyle": 0,
	"inProgressValueStyle": 0,
	"hash": 2190387136,
	"index": 2919,
	"redacted": false,
	"blacklisted": false
}