{
	"displayProperties": {
		"description": "",
		"name": "",
		"icon": "/common/destiny2_content/icons/e7eadf253fdf8e1a60edd7fb9ec1e4af.png",
		"iconSequences": [
			{
				"frames": [
					"/common/destiny2_content/icons/e7eadf253fdf8e1a60edd7fb9ec1e4af.png",
					"/common/destiny2_content/icons/9662e47f74160f8142210bceb0874443.png"
				]
			}
		],
		"hasIcon": true
	},
	"unlockValueHash": 0,
	"completionValue": 75000,
	"scope": 3,
	"locationHash": 0,
	"allowNegativeValue": false,
	"allowValueChangeWhenCompleted": true,
	"isCountingDownward": false,
	"valueStyle": 0,
	"progressDescription": "The number of targets eliminated as a Nightstalker.\n\nTracks from Season 1 onward.",
	"perks": {
		"perkHash": 0,
		"style": 0
	},
	"stats": {
		"style": 0
	},
	"minimumVisibilityThreshold": -2147483648,
	"allowOvercompletion": true,
	"showValueOnComplete": false,
	"isDisplayOnlyObjective": false,
	"completedValueStyle": 6,
	"inProgressValueStyle": 6,
	"hash": 2336777673,
	"index": 10,
	"redacted": false,
	"blacklisted": false
}