{
    "allowValueChangeWhenCompleted": true, 
    "isCountingDownward": false, 
    "redacted": false, 
    "progressDescription": "Crucible Opponents Defeated", 
    "unlockValueHash": 0, 
    "index": 4, 
    "stats": {
        "style": 0
    }, 
    "isDisplayOnlyObjective": false, 
    "allowNegativeValue": false, 
    "scope": 5, 
    "hash": 2439952408, 
    "completedValueStyle": 6, 
    "locationHash": 0, 
    "inProgressValueStyle": 6, 
    "showValueOnComplete": false, 
    "allowOvercompletion": true, 
    "valueStyle": 0, 
    "blacklisted": false, 
    "completionValue": 1, 
    "minimumVisibilityThreshold": -2147483648, 
    "perks": {
        "style": 0, 
        "perkHash": 0
    }, 
    "displayProperties": {
        "icon": "/common/destiny2_content/icons/f97862fcd4af9e2e9c5490e216d7ba5c.png", 
        "hasIcon": true, 
        "description": "", 
        "name": ""
    }
}