{
    "index": 86, 
    "groupCategoryOnly": false, 
    "grantDestinyClass": 3, 
    "blacklisted": false, 
    "shortTitle": "Clan Banners: Staff", 
    "grantDestinyItemType": 0, 
    "deprecated": false, 
    "redacted": false, 
    "grantDestinySubType": 0, 
    "itemTypeRegex": "(type_clan_staff)|(clan_staff)", 
    "parentCategoryHashes": [
        874645359, 
        59
    ], 
    "visible": false, 
    "groupedCategoryHashes": [], 
    "displayProperties": {
        "hasIcon": false, 
        "description": "These represent the 'staff' of the clan banner, which has its own benefits.", 
        "name": "Clan Banners: Staff"
    }, 
    "hash": 1873949940, 
    "isPlug": false, 
    "grantDestinyBreakerType": 0
}