{
    "index": 58, 
    "groupCategoryOnly": false, 
    "grantDestinyClass": 3, 
    "blacklisted": false, 
    "shortTitle": "Bonus Mods", 
    "grantDestinyItemType": 0, 
    "deprecated": false, 
    "redacted": false, 
    "grantDestinySubType": 0, 
    "itemTypeRegex": "(type_perk)|(type_armor_perk)", 
    "parentCategoryHashes": [
        59
    ], 
    "visible": false, 
    "groupedCategoryHashes": [], 
    "displayProperties": {
        "hasIcon": false, 
        "description": "Mods that provide conditional bonuses while you meet some qualifications/challenge.", 
        "name": "Bonus Mods"
    }, 
    "hash": 303512563, 
    "isPlug": false, 
    "grantDestinyBreakerType": 0
}