{
    "index": 25, 
    "groupCategoryOnly": false, 
    "grantDestinyClass": 3, 
    "blacklisted": false, 
    "shortTitle": "", 
    "grantDestinyItemType": 7, 
    "deprecated": true, 
    "redacted": false, 
    "grantDestinySubType": 0, 
    "itemTypeRegex": "type_message_.*", 
    "parentCategoryHashes": [], 
    "visible": false, 
    "groupedCategoryHashes": [], 
    "displayProperties": {
        "hasIcon": false, 
        "description": "", 
        "name": ""
    }, 
    "hash": 32, 
    "isPlug": false, 
    "grantDestinyBreakerType": 0
}