{
    "index": 60, 
    "groupCategoryOnly": false, 
    "grantDestinyClass": 3, 
    "blacklisted": false, 
    "shortTitle": "Armor Mods", 
    "grantDestinyItemType": 0, 
    "deprecated": false, 
    "redacted": false, 
    "grantDestinySubType": 0, 
    "parentCategoryHashes": [
        59
    ], 
    "visible": false, 
    "groupedCategoryHashes": [
        4062965806, 
        3872696960, 
        3723676689, 
        1362265421, 
        3607371986, 
        3196106184, 
        1742617626, 
        1875601085
    ], 
    "displayProperties": {
        "hasIcon": false, 
        "description": "Mods that can be applied, or are intrinsic on, armor.", 
        "name": "Armor Mods"
    }, 
    "hash": 4104513227, 
    "isPlug": false, 
    "grantDestinyBreakerType": 0
}