{
    "index": 570, 
    "traitHashes": [], 
    "nodeType": 1, 
    "blacklisted": false, 
    "presentationNodeType": 1, 
    "redacted": false, 
    "requirements": {
        "entitlementUnavailableMessage": ""
    }, 
    "objectiveHash": 3025965153, 
    "parentNodeHashes": [
        1194050975
    ], 
    "displayStyle": 0, 
    "screenStyle": 0, 
    "traitIds": [], 
    "disableChildSubscreenNavigation": false, 
    "displayProperties": {
        "hasIcon": false, 
        "description": "", 
        "name": "Season 7"
    }, 
    "scope": 0, 
    "children": {
        "metrics": [], 
        "collectibles": [
            {
                "collectibleHash": 4134213394
            }, 
            {
                "collectibleHash": 4134213395
            }, 
            {
                "collectibleHash": 4134213392
            }, 
            {
                "collectibleHash": 4134213393
            }, 
            {
                "collectibleHash": 4134213398
            }, 
            {
                "collectibleHash": 3216139398
            }, 
            {
                "collectibleHash": 3216139399
            }
        ], 
        "presentationNodes": [], 
        "records": []
    }, 
    "hash": 2662026551
}