{
	"displayProperties": {
		"description": "",
		"name": "Auto Rifles",
		"hasIcon": false
	},
	"nodeType": 2,
	"scope": 0,
	"objectiveHash": 392970015,
	"children": {
		"presentationNodes": [],
		"collectibles": [
			{
				"collectibleHash": 4140945370
			},
			{
				"collectibleHash": 1808035597
			},
			{
				"collectibleHash": 1378694235
			},
			{
				"collectibleHash": 4286897334
			},
			{
				"collectibleHash": 2259769907
			},
			{
				"collectibleHash": 897120837
			},
			{
				"collectibleHash": 4119829548
			},
			{
				"collectibleHash": 4193808083
			},
			{
				"collectibleHash": 3163448618
			},
			{
				"collectibleHash": 1126967188
			},
			{
				"collectibleHash": 2732095071
			},
			{
				"collectibleHash": 161074137
			}
		],
		"records": [],
		"metrics": []
	},
	"displayStyle": 0,
	"screenStyle": 0,
	"requirements": {
		"entitlementUnavailableMessage": ""
	},
	"disableChildSubscreenNavigation": false,
	"presentationNodeType": 1,
	"traitIds": [],
	"traitHashes": [],
	"parentNodeHashes": [
		1205461800
	],
	"hash": 2733721357,
	"index": 549,
	"redacted": false,
	"blacklisted": false
}