{
    "index": 89, 
    "traitHashes": [], 
    "nodeType": 2, 
    "blacklisted": false, 
    "presentationNodeType": 1, 
    "redacted": false, 
    "requirements": {
        "entitlementUnavailableMessage": ""
    }, 
    "objectiveHash": 3852814233, 
    "parentNodeHashes": [
        3707983485
    ], 
    "displayStyle": 0, 
    "screenStyle": 0, 
    "traitIds": [], 
    "disableChildSubscreenNavigation": false, 
    "displayProperties": {
        "hasIcon": false, 
        "description": "", 
        "name": "Sovereign Suit"
    }, 
    "scope": 0, 
    "children": {
        "metrics": [], 
        "collectibles": [
            {
                "collectibleHash": 903252957
            }, 
            {
                "collectibleHash": 1543192218
            }, 
            {
                "collectibleHash": 681290262
            }, 
            {
                "collectibleHash": 4196419544
            }, 
            {
                "collectibleHash": 1951882497
            }
        ], 
        "presentationNodes": [], 
        "records": []
    }, 
    "hash": 3219151823
}