{
	"displayProperties": {
		"description": "",
		"name": "Exodus Down Suit",
		"hasIcon": false
	},
	"nodeType": 2,
	"scope": 0,
	"objectiveHash": 3937752170,
	"children": {
		"presentationNodes": [],
		"collectibles": [
			{
				"collectibleHash": 338065032
			},
			{
				"collectibleHash": 3997010419
			},
			{
				"collectibleHash": 2909578869
			},
			{
				"collectibleHash": 1884532441
			},
			{
				"collectibleHash": 3902769578
			}
		],
		"records": [],
		"metrics": []
	},
	"displayStyle": 0,
	"screenStyle": 0,
	"requirements": {
		"entitlementUnavailableMessage": ""
	},
	"disableChildSubscreenNavigation": false,
	"presentationNodeType": 1,
	"traitIds": [],
	"traitHashes": [],
	"parentNodeHashes": [
		704930484
	],
	"hash": 3952745164,
	"index": 285,
	"redacted": false,
	"blacklisted": false
}