{
    "index": 702, 
    "traitHashes": [], 
    "nodeType": 1, 
    "blacklisted": false, 
    "presentationNodeType": 1, 
    "redacted": false, 
    "requirements": {
        "entitlementUnavailableMessage": ""
    }, 
    "objectiveHash": 779656396, 
    "parentNodeHashes": [
        1111248994
    ], 
    "displayStyle": 0, 
    "screenStyle": 0, 
    "traitIds": [], 
    "disableChildSubscreenNavigation": false, 
    "displayProperties": {
        "hasIcon": false, 
        "description": "", 
        "name": "Kinetic Weapons"
    }, 
    "scope": 1, 
    "children": {
        "metrics": [], 
        "collectibles": [], 
        "presentationNodes": [], 
        "records": [
            {
                "recordHash": 3904776877
            }, 
            {
                "recordHash": 3631669465
            }, 
            {
                "recordHash": 2660224414
            }, 
            {
                "recordHash": 1257836884
            }, 
            {
                "recordHash": 1366508788
            }, 
            {
                "recordHash": 1497347070
            }, 
            {
                "recordHash": 3812775859
            }, 
            {
                "recordHash": 1962727403
            }, 
            {
                "recordHash": 3121210389
            }, 
            {
                "recordHash": 2136108437
            }, 
            {
                "recordHash": 3783249575
            }, 
            {
                "recordHash": 3248675632
            }, 
            {
                "recordHash": 1576480714
            }, 
            {
                "recordHash": 2245186555
            }, 
            {
                "recordHash": 369883069
            }, 
            {
                "recordHash": 3180129357
            }
        ]
    }, 
    "hash": 4145555894
}